torch_snippets/__init__.py
torch_snippets/__module_timing__.py
torch_snippets/_modidx.py
torch_snippets/_nbdev.py
torch_snippets/adapters.py
torch_snippets/bb_utils.py
torch_snippets/bokeh_loader.py
torch_snippets/charts.py
torch_snippets/cli.py
torch_snippets/dates.py
torch_snippets/decorators.py
torch_snippets/fastcores.py
torch_snippets/icecream.py
torch_snippets/imgaug_loader.py
torch_snippets/inspector.py
torch_snippets/interactive_show.py
torch_snippets/ipython.py
torch_snippets/load_defaults.py
torch_snippets/loader.py
torch_snippets/logger.py
torch_snippets/markdown.py
torch_snippets/markup.py
torch_snippets/markup2.py
torch_snippets/misc.py
torch_snippets/paths.py
torch_snippets/pdf_loader.py
torch_snippets/profiler.py
torch_snippets/registry.py
torch_snippets/s3_loader.py
torch_snippets/s3_loader2.py
torch_snippets/scp.py
torch_snippets/sklegos.py
torch_snippets/text_utils.py
torch_snippets/tmp.py
torch_snippets/torch_loader.py
torch_snippets/video.py
torch_snippets/zen.py
torch_snippets/fasthtml/__init__.py
torch_snippets/fasthtml/chat.py
torch_snippets/thinc_parser/__init__.py
torch_snippets/thinc_parser/parser.py
torch_snippets/trainer/__init__.py
torch_snippets/trainer/capsule.py
torch_snippets/trainer/config.py
torch_snippets/trainer/hooks.py
torch_snippets/trainer/neural_graph.py
torch_snippets-0.560.dist-info/licenses/LICENSE
torch_snippets-0.560.dist-info/licenses/LICENSE.txt
torch_snippets-0.560.dist-info/METADATA
torch_snippets-0.560.dist-info/WHEEL
torch_snippets-0.560.dist-info/entry_points.txt
torch_snippets-0.560.dist-info/top_level.txt
torch_snippets-0.560.dist-info/RECORD
