Metadata-Version: 2.4
Name: torch_snippets
Version: 0.560
Summary: One line functions for common tasks
Home-page: https://github.com/sizhky/torch_snippets/tree/master/
Author: Yeshwanth Reddy
Author-email: 1992chinna@gmail.com
License: Apache Software License 2.0
Keywords: snippets,torch
Classifier: Development Status :: 3 - Alpha
Classifier: Intended Audience :: Developers
Classifier: License :: OSI Approved :: Apache Software License
Classifier: Natural Language :: English
Classifier: Programming Language :: Python :: 3.7
Classifier: Programming Language :: Python :: 3.8
Requires-Python: >=3.7
License-File: LICENSE
License-File: LICENSE.txt
Requires-Dist: plum-dispatch
Requires-Dist: fastcore
Requires-Dist: matplotlib
Requires-Dist: Pillow
Requires-Dist: dill
Requires-Dist: loguru
Requires-Dist: numpy
Requires-Dist: pandas
Requires-Dist: tqdm
Requires-Dist: rich
Requires-Dist: PyYAML
Requires-Dist: catalogue
Requires-Dist: confection
Requires-Dist: pydantic
Requires-Dist: typing
Requires-Dist: srsly
Requires-Dist: typing_extensions
Requires-Dist: wasabi
Requires-Dist: jsonlines
Requires-Dist: imgaug>=0.4.0
Requires-Dist: xmltodict
Requires-Dist: fuzzywuzzy
Requires-Dist: nltk
Requires-Dist: python-Levenshtein
Requires-Dist: pre-commit
Requires-Dist: icecream
Requires-Dist: mergedeep
Requires-Dist: deepdiff
Requires-Dist: typer
Requires-Dist: torch
Requires-Dist: torchvision
Requires-Dist: lovely_tensors
Provides-Extra: torch
Requires-Dist: torch; extra == "torch"
Requires-Dist: torchvision; extra == "torch"
Requires-Dist: lovely_tensors; extra == "torch"
Provides-Extra: altair
Requires-Dist: altair; extra == "altair"
Provides-Extra: bokeh
Requires-Dist: bokeh; extra == "bokeh"
Provides-Extra: pdf
Requires-Dist: pymupdf; extra == "pdf"
Provides-Extra: jupyter
Requires-Dist: nbconvert; extra == "jupyter"
Requires-Dist: nbformat; extra == "jupyter"
Requires-Dist: ipython; extra == "jupyter"
Dynamic: author
Dynamic: author-email
Dynamic: classifier
Dynamic: description
Dynamic: description-content-type
Dynamic: home-page
Dynamic: keywords
Dynamic: license
Dynamic: license-file
Dynamic: provides-extra
Dynamic: requires-dist
Dynamic: requires-python
Dynamic: summary
